lxlog/__init__.py
lxlog/lxlog.py
lxlog-0.11.0.dist-info/METADATA
lxlog-0.11.0.dist-info/WHEEL
lxlog-0.11.0.dist-info/top_level.txt
lxlog-0.11.0.dist-info/RECORD
